LICENSE.md
lock_defaults/__init__.py
lock_defaults/py.typed
lock_defaults/with_paramspec/lock_defaults.py
lock_defaults/without_paramspec/lock_defaults.py
lock_defaults-0.1.4.dist-info/LICENSE.md
lock_defaults-0.1.4.dist-info/WHEEL
lock_defaults-0.1.4.dist-info/METADATA
lock_defaults-0.1.4.dist-info/RECORD
