Metadata-Version: 2.1
Name: lock-defaults
Version: 0.1.4
Summary: Helper decorator to lock default mutable values
Home-page: https://github.com/ajparsons/lock-defaults
License: MIT
Author: Alex Parsons
Author-email: alex@alexparsons.co.uk
Requires-Python: >=3.8,<4.0
Classifier: License :: OSI Approved :: MIT License
Classifier: Programming Language :: Python :: 3
Classifier: Programming Language :: Python :: 3.10
Classifier: Programming Language :: Python :: 3.8
Classifier: Programming Language :: Python :: 3.9
Project-URL: Repository, https://github.com/ajparsons/lock-defaults
